langchain_coherence/__init__.py
langchain_coherence/coherence_store.py
langchain_coherence-0.0.3.dist-info/licenses/LICENSE
langchain_coherence-0.0.3.dist-info/METADATA
langchain_coherence-0.0.3.dist-info/WHEEL
langchain_coherence-0.0.3.dist-info/top_level.txt
langchain_coherence-0.0.3.dist-info/RECORD
