Metadata-Version: 2.4
Name: langchain-coherence
Version: 0.0.3
Summary: LangChain integration for Oracle Coherence as a vector store.
Author-email: Your Name <you@example.com>
License: MIT
Project-URL: Source Code, https://github.com/langchain-ai/langchain/tree/master/libs/partners/coherence
Project-URL: repository, https://github.com/langchain-ai/langchain
Requires-Python: >=3.9
License-File: LICENSE
Requires-Dist: langchain-core>=0.1.20
Requires-Dist: coherence-client>=2.0.4
Dynamic: license-file
